{
    "beamjoy.common.loading": "로딩 중...",
    "beamjoy.common.and": "그리고",
    "beamjoy.common.enabled": "사용",
    "beamjoy.common.disabled": "사용 안 함",
    "beamjoy.common.invalid": "잘못됨",
    "beamjoy.common.reset": "재설정",
    "beamjoy.common.preview": "미리보기",
    "beamjoy.common.confirm": "확인",
    "beamjoy.common.cancel": "취소",
    "beamjoy.common.apply": "적용",
    "beamjoy.common.save": "저장",
    "beamjoy.common.add": "추가",
    "beamjoy.common.create": "생성",
    "beamjoy.common.remove": "제거",
    "beamjoy.common.noMatches": "일치 항목 없음",
    "beamjoy.groups.default": "기본",
    "beamjoy.groups.player": "플레이어",
    "beamjoy.groups.vip": "VIP",
    "beamjoy.groups.mod": "모드",
    "beamjoy.groups.admin": "관리자",
    "beamjoy.groups.owner": "소유자",
    "beamjoy.groups.staffMark": "STAFF",

    "beamjoy.time.second": "초",
    "beamjoy.time.seconds": "초",
    "beamjoy.time.minute": "분",
    "beamjoy.time.minutes": "분",
    "beamjoy.time.hour": "시간",
    "beamjoy.time.hours": "시간",
    "beamjoy.time.day": "일",
    "beamjoy.time.days": "일",
    "beamjoy.time.month": "월",
    "beamjoy.time.months": "월",

    "beamjoy.types.boolean": "불리언",
    "beamjoy.types.number": "숫자",
    "beamjoy.types.string": "문자열",

    "ui.options.controls.bindings.beamjoy": "BeamJoy",
    "ui.inputActions.beamjoy.toggleMenu.title": "메뉴 전환",
    "ui.inputActions.beamjoy.toggleMenu.description": "메뉴 바 표시/숨기기",

    "beamjoy.menu.toggleMain": "BeamJoy",
    "beamjoy.menu.toggleConfig": "설정",
    "beamjoy.menu.switchMap": "맵",
    "beamjoy.menu.showIntroPanel": "환영 화면",
    "beamjoy.menu.about": "정보",
    "beamjoy.menu.about.label": "BeamJoy Abstract v{version}, 빌드 {buildversion}",
    "beamjoy.menu.about.createdBy": "제작자: TontonSamael",
    "beamjoy.menu.about.computerTime": "컴퓨터 시간: {time}",

    "beamjoy.window.main": "BeamJoy 메인",
    "beamjoy.window.main.title": "BeamJoy",
    "beamjoy.window.main.tabs.main.title": "메인",
    "beamjoy.window.main.tabs.main.toggleNametags": "이름표 토글",
    "beamjoy.window.main.playerlist.title": "플레이어",
    "beamjoy.window.main.moderation.demote": "{groupName}로 강등",
    "beamjoy.window.main.moderation.promote": "{groupName}로 승격",
    "beamjoy.window.main.playerlist.actions.focus": "관전",
    "beamjoy.window.main.playerlist.actions.freeze": "정지",
    "beamjoy.window.main.playerlist.actions.freezeAll": "모두 정지",
    "beamjoy.window.main.playerlist.actions.unfreeze": "정지 해제",
    "beamjoy.window.main.playerlist.actions.unfreezeAll": "모두 정지 해제",
    "beamjoy.window.main.playerlist.actions.stop": "엔진 정지",
    "beamjoy.window.main.playerlist.actions.stopAll": "모든 엔진 정지",
    "beamjoy.window.main.playerlist.actions.start": "엔진 시작",
    "beamjoy.window.main.playerlist.actions.startAll": "모든 엔진 시작",
    "beamjoy.window.main.playerlist.actions.delete": "제거",
    "beamjoy.window.main.playerlist.actions.deleteAll": "모두 제거",
    "beamjoy.window.main.playerlist.actions.explode": "폭발",
    "beamjoy.window.main.playerlist.moderation.previousMuteReason": "이전 뮤트 이유",
    "beamjoy.window.main.playerlist.moderation.muted": "뮤트됨",
    "beamjoy.window.main.playerlist.moderation.muteReason": "뮤트 이유",
    "beamjoy.window.main.playerlist.moderation.mute": "뮤트",
    "beamjoy.window.main.playerlist.moderation.unmute": "뮤트 해제",
    "beamjoy.window.main.playerlist.moderation.previousKickReason": "이전 킥 이유",
    "beamjoy.window.main.playerlist.moderation.kickReason": "킥 이유",
    "beamjoy.window.main.playerlist.moderation.kick": "킥",
    "beamjoy.window.main.playerlist.moderation.previousBanReason": "이전 밴 이유",
    "beamjoy.window.main.playerlist.moderation.banReason": "밴 이유",
    "beamjoy.window.main.playerlist.moderation.ban": "밴",
    "beamjoy.window.main.playerlist.moderation.tempbanDuration": "임시 밴 기간",
    "beamjoy.window.main.playerlist.moderation.tempban": "임시 밴",
    "beamjoy.window.main.playerlist.vehicles.title": "차량",
    "beamjoy.window.main.playerlist.vehicles.trafficCount": "{count} 교통 차량",
    "beamjoy.window.main.tabs.settings.title": "설정",
    "beamjoy.window.main.tabs.settings.sections.vehicle.title": "차량",
    "beamjoy.window.main.tabs.settings.sections.vehicle.automaticLights": "자동 라이트",
    "beamjoy.window.main.tabs.settings.sections.vehicle.automaticLights.tooltip": "시간에 따라 헤드라이트 자동 켜기",
    "beamjoy.window.main.tabs.settings.sections.nametags.title": "이름표",
    "beamjoy.window.main.tabs.settings.sections.nametags.showSpectators": "관전자 표시",
    "beamjoy.window.main.tabs.settings.sections.nametags.nameTagsHideBehindObjects": "관전자 이름표 표시",
    "beamjoy.window.main.tabs.settings.sections.nametags.playerColor": "플레이어 이름 색상",
    "beamjoy.window.main.tabs.settings.sections.nametags.playerBgColor": "플레이어 배경 색상",
    "beamjoy.window.main.tabs.settings.sections.nametags.idleColor": "대기 색상",
    "beamjoy.window.main.tabs.settings.sections.nametags.idleBgColor": "대기 배경 색상",
    "beamjoy.window.main.tabs.settings.sections.nametags.specColor": "관전자 색상",
    "beamjoy.window.main.tabs.settings.sections.nametags.specBgColor": "관전자 배경 색상",
    "beamjoy.window.main.tabs.settings.sections.freecam.title": "자유 카메라",
    "beamjoy.window.main.tabs.settings.sections.freecam.smooth": "부드러운 움직임",
    "beamjoy.window.main.tabs.settings.sections.freecam.fov": "시야각",
    "beamjoy.window.main.tabs.settings.sections.freecam.speed": "이동 속도",

    "beamjoy.window.config": "BeamJoy 서버 설정",
    "beamjoy.window.config.title": "서버 설정",
    "beamjoy.window.config.editor.gizmo.translate": "이동",
    "beamjoy.window.config.editor.gizmo.rotate": "회전",
    "beamjoy.window.config.editor.gizmo.scale": "확대/축소",
    "beamjoy.window.config.tabs.general.title": "일반",
    "beamjoy.window.config.tabs.general.allowMods": "플레이어 모드 허용",
    "beamjoy.window.config.tabs.general.allowMods.tooltip": "플레이어가 로컬 모드 사용 가능 (클라이언트 측)",
    "beamjoy.window.config.tabs.general.whitelist": "화이트리스트",
    "beamjoy.window.config.tabs.general.whitelist.status": "상태",
    "beamjoy.window.config.tabs.general.whitelist.addAll": "모든 연결된 플레이어 추가",
    "beamjoy.window.config.tabs.general.whitelist.players": "플레이어",
    "beamjoy.window.config.tabs.general.whitelist.addOffline": "오프라인 플레이어 추가",
    "beamjoy.window.config.tabs.general.whitelist.addOffline.tooltip": "대소문자 구분",
    "beamjoy.window.config.tabs.general.intropanel": "환영 화면",
    "beamjoy.window.config.tabs.general.intropanel.enabled": "상태",
    "beamjoy.window.config.tabs.general.intropanel.onlyFirstConnection": "처음 연결 시만",
    "beamjoy.window.config.tabs.general.intropanel.onlyFirstConnection.tooltip": "체크하면 첫 연결 시에만 환영 화면 표시",
    "beamjoy.window.config.tabs.general.intropanel.title": "제목",
    "beamjoy.window.config.tabs.general.intropanel.content": "내용",
    "beamjoy.window.config.tabs.general.intropanel.content.tooltip": "이 필드는 완전히 HTML 호환됩니다.\n '<'는 '&lt;'로 입력해야 합니다.\n '{player_name}', '{server_name}', '{players_count}' 변수를 사용 가능",
    "beamjoy.window.config.tabs.general.intropanel.image": "이미지",
    "beamjoy.window.config.tabs.general.chat": "채팅",
    "beamjoy.window.config.tabs.general.chat.ServerNameColor": "서버/스태프 태그 색상",
    "beamjoy.window.config.tabs.general.chat.ServerTextColor": "서버 메시지 색상",
    "beamjoy.window.config.tabs.general.chat.EventColor": "이벤트 메시지 색상",
    "beamjoy.window.config.tabs.general.chat.BroadcastColor": "공지 색상",
    "beamjoy.window.config.tabs.general.chat.ShowStaffTag": "스태프 태그 표시",
    "beamjoy.window.config.tabs.general.chat.WelcomeMessage": "환영 메시지",
    "beamjoy.window.config.tabs.general.modelBlacklist": "차량 블랙리스트",
    "beamjoy.window.config.tabs.general.modelBlacklist.models": "모델:",
    "beamjoy.window.config.tabs.general.traffic": "교통",
    "beamjoy.window.config.tabs.general.traffic.enabled": "교통 상태",
    "beamjoy.window.config.tabs.general.traffic.amount": "차량 수",
    "beamjoy.window.config.tabs.general.traffic.maxPerPlayer": "플레이어당 최대 차량",
    "beamjoy.window.config.tabs.general.traffic.minDistance": "최소 거리",
    "beamjoy.window.config.tabs.general.traffic.maxDistance": "최대 거리",
    "beamjoy.window.config.tabs.general.traffic.model": "모델",
    "beamjoy.window.config.tabs.general.environment": "시간 & 환경",
    "beamjoy.window.config.tabs.general.environment.openSettings": "환경 설정 열기",
    "beamjoy.window.config.tabs.general.environment.timeSync": "시간 동기화",
    "beamjoy.window.config.tabs.general.environment.dayLength": "주야 주기 길이",
    "beamjoy.window.config.tabs.general.environment.nightBrightnessMultiplier": "야간 밝기 배율",
    "beamjoy.window.config.tabs.general.environment.gravitySync": "중력 동기화",
    "beamjoy.window.config.tabs.general.broadcasts": "공지",
    "beamjoy.window.config.tabs.general.broadcasts.enabled": "상태",
    "beamjoy.window.config.tabs.general.broadcasts.delay": "지연",
    "beamjoy.window.config.tabs.general.broadcasts.messages": "메시지",
    "beamjoy.window.config.tabs.general.broadcasts.message": "메시지",
    "beamjoy.window.config.tabs.permissions.title": "권한",
    "beamjoy.window.config.tabs.permissions.groups": "그룹",
    "beamjoy.window.config.tabs.permissions.groups.level": "레벨",
    "beamjoy.window.config.tabs.permissions.groups.vehicleCap": "차량 한도",
    "beamjoy.window.config.tabs.permissions.groups.staff": "스태프",
    "beamjoy.window.config.tabs.permissions.groups.banned": "밴됨",
    "beamjoy.window.config.tabs.permissions.groups.muted": "뮤트됨",
    "beamjoy.window.config.tabs.permissions.groups.whitelisted": "화이트리스트",
    "beamjoy.window.config.tabs.permissions.groups.permissions": "권한",
    "beamjoy.window.config.tabs.permissions.groups.chatNameColor": "채팅 이름 색상",
    "beamjoy.window.config.tabs.permissions.groups.chatTextColor": "채팅 글자 색상",
    "beamjoy.window.config.tabs.permissions.permissions": "권한",
    "beamjoy.window.config.tabs.maps.title": "맵",
    "beamjoy.window.config.tabs.maps.active": "사용 가능한 맵",
    "beamjoy.window.config.tabs.maps.ignored": "사용 불가 맵",
    "beamjoy.window.config.tabs.maps.ignored.tooltip": "이전에 활성화된 모드 맵이지만 현재 없음",
    "beamjoy.window.config.tabs.maps.vanilla": "바닐라 맵",
    "beamjoy.window.config.tabs.core.title": "코어 설정",
    "beamjoy.window.config.tabs.core.fields.name": "이름",
    "beamjoy.window.config.tabs.core.fields.preview": "미리보기",
    "beamjoy.window.config.tabs.core.fields.preview.tooltip": "서버가 오프라인일 때 즐겨찾기 섹션에서 '[OFFLINE]' 접미사 표시",
    "beamjoy.window.config.tabs.core.fields.description": "설명",
    "beamjoy.window.config.tabs.core.fields.maxPlayers": "플레이어 제한",
    "beamjoy.window.config.tabs.core.fields.maxPlayers.tooltip": "스태프 플레이어는 제한 우회 가능",
    "beamjoy.window.config.tabs.core.fields.private": "비공개",
    "beamjoy.window.config.tabs.core.fields.private.tooltip": "서버 브라우저에서 서버 숨김",
    "beamjoy.window.config.tabs.core.fields.debug": "디버그 모드",
    "beamjoy.window.config.tabs.core.fields.debug.tooltip": "개발자/자세한 모드 활성화",
    "beamjoy.window.config.tabs.core.fields.informationPacket": "정보 패킷",
    "beamjoy.window.config.tabs.core.fields.informationPacket.tooltip": "플레이어가 접속하지 않고도 서버 정보 확인 가능",
    "beamjoy.window.config.tabs.database.title": "데이터베이스",
    "beamjoy.window.config.tabs.database.muteReason": "뮤트 이유",
    "beamjoy.window.config.tabs.database.muted": "뮤트됨",
    "beamjoy.window.config.tabs.database.muteReason.last": "최근 뮤트 이유",
    "beamjoy.window.config.tabs.database.kickReason": "최근 킥 이유",
    "beamjoy.window.config.tabs.database.banned": "밴됨",
    "beamjoy.window.config.tabs.database.banReason": "밴 이유",
    "beamjoy.window.config.tabs.database.banReason.last": "최근 밴 이유",
    "beamjoy.window.config.tabs.database.unban": "밴 해제",
    "beamjoy.window.config.tabs.database.data": "플레이어 데이터",
    "beamjoy.window.config.tabs.database.data.add": "데이터 추가",
    "beamjoy.window.config.tabs.database.data.keyPlaceholder": "키",
    "beamjoy.window.config.tabs.database.data.valuePlaceholder": "값",
    "beamjoy.window.config.tabs.safeZones.title": "안전 구역",
    "beamjoy.activities.tabs.safeZones.createZone": "이곳에 구역 생성",
    "beamjoy.activities.tabs.safeZones.duplicateZone": "이곳에 구역 복제",
    "beamjoy.activities.tabs.safeZones.deleteZone": "구역 삭제",

    "beamjoy.window.hud": "BeamJoy HUD",

    "beamjoy.toast.vehicleSelector.removeOtherVeh": "다른 플레이어의 차량을 제거하려고 합니다. 진행하시겠습니까?",
    "beamjoy.toast.traffic.waitForSpawn": "교통 차량 생성 중... 잠시만 기다려주세요.",
    "beamjoy.toast.mods.cannotDisableMandatory": "이 모드는 제거할 수 없습니다!",
    "beamjoy.toast.mods.managingNotAllowed": "서버에서 모드 관리가 허용되지 않습니다!",
    "beamjoy.toast.traffic.policeDisabled": "서버에서 경찰 AI가 비활성화되었습니다.",

    "beamjoy.chat.senderServer": "서버",
    "beamjoy.chat.event.playerJoined": "{playerName}이 서버에 접속했습니다",
    "beamjoy.chat.event.playerLeft": "{playerName}이 서버를 나갔습니다",

    "beamjoy.activities.safeZone.label": "안전 구역",

    "beamjoy.nametags.you": "당신",
    "beamjoy.nametags.yourTrailer": "당신의 트레일러",
    "beamjoy.nametags.othersTrailer": "{playerName}의 트레일러",

    "beamjoy.moderation.confirm.mute": "{playerName}을(를) 뮤트하시겠습니까?",
    "beamjoy.moderation.confirm.muteWithReason": "{playerName}을(를) '{reason}' 이유로 뮤트하시겠습니까?",
    "beamjoy.moderation.confirm.kick": "{playerName}을(를) 킥하시겠습니까?",
    "beamjoy.moderation.confirm.kickWithReason": "{playerName}을(를) '{reason}' 이유로 킥하시겠습니까?",
    "beamjoy.moderation.confirm.ban": "{playerName}을(를) 밴하시겠습니까?",
    "beamjoy.moderation.confirm.banWithReason": "{playerName}을(를) '{reason}' 이유로 밴하시겠습니까?",
    "beamjoy.moderation.confirm.tempban": "{playerName}을(를) {duration} 동안 임시 밴하시겠습니까?",
    "beamjoy.moderation.confirm.tempbanWithReason": "{playerName}을(를) {duration} 동안 '{reason}' 이유로 임시 밴하시겠습니까?",

    "beamjoy.core.formatting.0": "검정",
    "beamjoy.core.formatting.1": "파랑",
    "beamjoy.core.formatting.2": "초록",
    "beamjoy.core.formatting.3": "청록",
    "beamjoy.core.formatting.4": "빨강",
    "beamjoy.core.formatting.5": "보라",
    "beamjoy.core.formatting.6": "주황",
    "beamjoy.core.formatting.7": "회색",
    "beamjoy.core.formatting.8": "짙은 회색",
    "beamjoy.core.formatting.9": "연한 파랑",
    "beamjoy.core.formatting.a": "연한 초록",
    "beamjoy.core.formatting.b": "아쿠아",
    "beamjoy.core.formatting.c": "연한 빨강",
    "beamjoy.core.formatting.d": "분홍",
    "beamjoy.core.formatting.e": "노랑",
    "beamjoy.core.formatting.f": "흰색",
    "beamjoy.core.formatting.r": "리셋",
    "beamjoy.core.formatting.l": "굵게",
    "beamjoy.core.formatting.m": "취소선",
    "beamjoy.core.formatting.n": "밑줄",
    "beamjoy.core.formatting.o": "기울임",

    "beamjoy.broadcasts.mapChangeKick": "맵이 변경되었습니다. {time}초 후에 킥됩니다.",
    "beamjoy.broadcasts.stop.countdownBroadcast": "서버가 {seconds}초 후에 종료됩니다.",

    "beamjoy.pursuit.arrestIn": "{time} 후 체포",
    "beamjoy.pursuit.fugitiveTag": "도주자"
}
